Metadata-Version: 2.1
Name: clothes-sdk-ashuk203
Version: 1.0.6
Summary: Python SDK for (dummy) Clothes APIs
Home-page: 
Author: Ashutosh Ukey
Author-email: ashuk203@gmail.com
Keywords: OpenAPI,OpenAPI-Generator,Clothes Warehouse
Requires-Python: >=3.7
License-File: LICENSE
Requires-Dist: certifi (>=14.5.14)
Requires-Dist: frozendict (~=2.3.4)
Requires-Dist: python-dateutil (~=2.7.0)
Requires-Dist: setuptools (>=21.0.0)
Requires-Dist: typing-extensions (~=4.3.0)
Requires-Dist: urllib3 (~=1.26.7)
